{
  "generatedAt": "2026-07-13T06:22:22.994218+00:00",
  "index": {
    "baseDate": "2023-04-01",
    "baseValue": 1000.0,
    "value": 2049.7,
    "prevValue": 2047.67,
    "changePct": 0.1
  },
  "companyCount": 16,
  "failedCount": 0,
  "companies": [
    {
      "symbol": "ADANIPORTS",
      "name": "Adani Ports & SEZ (APSEZ)",
      "segment": "Ports / SEZ",
      "price": 1812.0,
      "prevClose": 1829.9,
      "changePct": -0.98,
      "marketCapCr": 417477.4,
      "status": "ok"
    },
    {
      "symbol": "JSWINFRA",
      "name": "JSW Infrastructure",
      "segment": "Ports / Terminals",
      "price": 350.35,
      "prevClose": 329.05,
      "changePct": 6.47,
      "marketCapCr": 81111.7,
      "status": "ok"
    },
    {
      "symbol": "AEGISLOG",
      "name": "Aegis Logistics",
      "segment": "LPG / Liquid Terminals",
      "price": 1270.9,
      "prevClose": 1234.0,
      "changePct": 2.99,
      "marketCapCr": 44608.6,
      "status": "ok"
    },
    {
      "symbol": "DELHIVERY",
      "name": "Delhivery Ltd",
      "segment": "E-commerce / 3PL",
      "price": 512.7,
      "prevClose": 519.0,
      "changePct": -1.21,
      "marketCapCr": 38393.4,
      "status": "ok"
    },
    {
      "symbol": "CONCOR",
      "name": "Container Corp. of India",
      "segment": "Rail / Container",
      "price": 458.55,
      "prevClose": 463.8,
      "changePct": -1.13,
      "marketCapCr": 34924.0,
      "status": "ok"
    },
    {
      "symbol": "GESHIP",
      "name": "Great Eastern Shipping",
      "segment": "Shipping",
      "price": 1394.6,
      "prevClose": 1425.0,
      "changePct": -2.13,
      "marketCapCr": 19910.3,
      "status": "ok"
    },
    {
      "symbol": "SCI",
      "name": "Shipping Corp. of India",
      "segment": "Shipping",
      "price": 284.8,
      "prevClose": 285.55,
      "changePct": -0.26,
      "marketCapCr": 13266.0,
      "status": "ok"
    },
    {
      "symbol": "BLUEDART",
      "name": "Blue Dart Express",
      "segment": "Air / Express",
      "price": 4903.3,
      "prevClose": 4918.4,
      "changePct": -0.31,
      "marketCapCr": 11634.5,
      "status": "ok"
    },
    {
      "symbol": "TCI",
      "name": "Transport Corp. of India",
      "segment": "Multimodal",
      "price": 933.35,
      "prevClose": 935.25,
      "changePct": -0.2,
      "marketCapCr": 7171.0,
      "status": "ok"
    },
    {
      "symbol": "TVSSCS",
      "name": "TVS Supply Chain Solutions",
      "segment": "3PL / Supply Chain",
      "price": 140.26,
      "prevClose": 141.66,
      "changePct": -0.99,
      "marketCapCr": 6188.0,
      "status": "ok"
    },
    {
      "symbol": "VRLLOG",
      "name": "VRL Logistics",
      "segment": "Surface Freight",
      "price": 232.3,
      "prevClose": 231.21,
      "changePct": 0.47,
      "marketCapCr": 4063.8,
      "status": "ok"
    },
    {
      "symbol": "MAHLOG",
      "name": "Mahindra Logistics",
      "segment": "3PL / Supply Chain",
      "price": 386.05,
      "prevClose": 387.2,
      "changePct": -0.3,
      "marketCapCr": 3830.5,
      "status": "ok"
    },
    {
      "symbol": "TCIEXP",
      "name": "TCI Express",
      "segment": "Surface Express",
      "price": 563.25,
      "prevClose": 559.75,
      "changePct": 0.63,
      "marketCapCr": 2163.9,
      "status": "ok"
    },
    {
      "symbol": "NAVKARCORP",
      "name": "Navkar Corporation",
      "segment": "ICD / Container",
      "price": 109.25,
      "prevClose": 109.2,
      "changePct": 0.05,
      "marketCapCr": 1644.4,
      "status": "ok"
    },
    {
      "symbol": "ALLCARGO",
      "name": "Allcargo Logistics",
      "segment": "Freight Forwarding",
      "price": 8.01,
      "prevClose": 7.95,
      "changePct": 0.75,
      "marketCapCr": 1199.7,
      "status": "ok"
    },
    {
      "symbol": "SNOWMAN",
      "name": "Snowman Logistics",
      "segment": "Cold Chain",
      "price": 36.5,
      "prevClose": 36.26,
      "changePct": 0.66,
      "marketCapCr": 610.3,
      "status": "ok"
    }
  ]
}